finplot/__init__.py
finplot/_version.py
finplot/live.py
finplot/pdplot.py
finplot-1.9.7.dist-info/LICENSE.txt
finplot-1.9.7.dist-info/METADATA
finplot-1.9.7.dist-info/WHEEL
finplot-1.9.7.dist-info/top_level.txt
finplot-1.9.7.dist-info/RECORD
