Metadata-Version: 2.1
Name: finplot
Version: 1.9.7
Summary: Finance plotting
Home-page: https://github.com/highfestiva/finplot
Author: Jonas Byström
Author-email: highfestiva@gmail.com
Classifier: Programming Language :: Python :: 3
Classifier: License :: OSI Approved :: MIT License
Classifier: Operating System :: OS Independent
License-File: LICENSE.txt
Requires-Dist: numpy (>=1.23.5)
Requires-Dist: pandas (>=1.5.2)
Requires-Dist: PyQt6 (>=6.4.0)
Requires-Dist: pyqtgraph (>=0.13.1)
Requires-Dist: python-dateutil
